Esteganew/__init__.py
Esteganew/esteganew.py
esteganew-0.1.dist-info/LICENSE
esteganew-0.1.dist-info/METADATA
esteganew-0.1.dist-info/WHEEL
esteganew-0.1.dist-info/top_level.txt
esteganew-0.1.dist-info/RECORD
