Metadata-Version: 2.1
Name: esteganew
Version: 0.1
Summary: Steganographic tool, for images.
Home-page: https://github.com/JuanPab3/esteganew
Author: JuanPab3 and naso071699
Author-email: juanpab.sierra@urosario.edu.co
License: UNKNOWN
Platform: UNKNOWN
Classifier: Programming Language :: Python :: 3
Classifier: License :: OSI Approved :: MIT License
Classifier: Operating System :: OS Independent
Requires-Python: >=3.6
